stocki/__init__.py
stocki/__main__.py
stocki/stocki.py
stocki/stocki.pyc
stocki-0.2.0.dist-info/LICENSE.txt
stocki-0.2.0.dist-info/METADATA
stocki-0.2.0.dist-info/WHEEL
stocki-0.2.0.dist-info/entry_points.txt
stocki-0.2.0.dist-info/top_level.txt
stocki-0.2.0.dist-info/RECORD
