Metadata-Version: 2.1
Name: stocki
Version: 0.2.0
Summary: The CLI for fetching stock market data.
Home-page: https://github.com/andrewrporter/stocki
Author: AndrewRPorter
Author-email: porter.r.andrew@gmail.com
License: MIT License
Requires-Dist: pycodestyle
Requires-Dist: requests
Requires-Dist: urwid
